carpet_concentrations/__init__.py
carpet_concentrations/attrs_utils.py
carpet_concentrations/exceptions.py
carpet_concentrations/gridders/__init__.py
carpet_concentrations/gridders/latitude_seasonality_gridder.py
carpet_concentrations/input4MIPs/__init__.py
carpet_concentrations/input4MIPs/dataset.py
carpet_concentrations/input4MIPs/metadata_options.py
carpet_concentrations/py.typed
carpet_concentrations/testing.py
carpet_concentrations/time.py
carpet_concentrations/xarray_pint_utils.py
carpet_concentrations/xarray_utils.py
carpet_concentrations-0.5.1.dist-info/LICENSE
carpet_concentrations-0.5.1.dist-info/METADATA
carpet_concentrations-0.5.1.dist-info/WHEEL
carpet_concentrations-0.5.1.dist-info/RECORD
