Metadata-Version: 2.1
Name: carpet-concentrations
Version: 0.5.1
Summary: Core tools for the development of greenhouse gas concentration input files (i.e. flying carpets).
License: BSD-3-Clause
Author: Zebedee Nicholls
Author-email: zebedee.nicholls@climate-resource.com
Requires-Python: >=3.9,<4.0
Classifier: License :: OSI Approved :: BSD License
Classifier: Programming Language :: Python :: 3
Classifier: Programming Language :: Python :: 3.9
Classifier: Programming Language :: Python :: 3.10
Classifier: Programming Language :: Python :: 3.11
Classifier: Programming Language :: Python :: 3.12
Provides-Extra: cfxarray
Provides-Extra: netcdf
Provides-Extra: notebooks
Provides-Extra: plots
Requires-Dist: attrs (>=22.0)
Requires-Dist: cf-xarray (>=0.8) ; extra == "cfxarray"
Requires-Dist: cftime (>=1.6)
Requires-Dist: ipywidgets (>=8.0) ; extra == "notebooks"
Requires-Dist: matplotlib (>=3.7)
Requires-Dist: netcdf4 (>=1.0) ; extra == "netcdf"
Requires-Dist: notebook (>=6.0) ; extra == "notebooks"
Requires-Dist: openscm-units (>=0.5)
Requires-Dist: pint (>=0.19)
Requires-Dist: pint-xarray (>=0.3)
Requires-Dist: pooch (>=1.0) ; extra == "cfxarray"
Requires-Dist: seaborn (>=0.12) ; extra == "plots"
Requires-Dist: xarray (>=2022.0)
